arghandler/__init__.py
arghandler/base.py
arghandler/test.py
arghandler/tests/__init__.py
arghandler/tests/base.py
arghandler/tests/decorator.py
arghandler/tests/decorator2.py
arghandler/tests/subcmds.py
arghandler/tests/subcmds1.py
arghandler-1.3.1.dist-info/METADATA
arghandler-1.3.1.dist-info/RECORD
arghandler-1.3.1.dist-info/WHEEL
arghandler-1.3.1.dist-info/top_level.txt
