Metadata-Version: 2.1
Name: arghandler
Version: 1.3.1
Summary: argparse extended with awesome feature enhancements to make life easier
Home-page: http://www.github.com/druths/arghandler
Author: Derek Ruths
Author-email: druths@networkdynamics.org
License: Apache
Keywords: argparse command-line parsing
Platform: UNKNOWN
Classifier: Development Status :: 4 - Beta
Classifier: Intended Audience :: Developers
Classifier: Topic :: Software Development
Classifier: License :: OSI Approved :: Apache Software License
Classifier: Programming Language :: Python :: 2.7
Classifier: Programming Language :: Python :: 3
Classifier: Programming Language :: Python :: 3.2
Classifier: Programming Language :: Python :: 3.3
Classifier: Programming Language :: Python :: 3.4
